[
    {
        "id": 6206170245103616,
        "weather_state_name": "Light Cloud",
        "weather_state_abbr": "lc",
        "wind_direction_compass": "SW",
        "created": "2020-03-01T21:16:01.577747Z",
        "applicable_date": "2020-03-01",
        "min_temp": 4.565,
        "max_temp": 7.385,
        "the_temp": 7.19,
        "wind_speed": 10.990444571566053,
        "wind_direction": 236.15978082168533,
        "air_pressure": 989.0,
        "humidity": 59,
        "visibility": 10.77209098862642,
        "predictability": 70
    },
    {
        "id": 4732424023965696,
        "weather_state_name": "Light Rain",
        "weather_state_abbr": "lr",
        "wind_direction_compass": "WSW",
        "created": "2020-03-01T18:16:03.274235Z",
        "applicable_date": "2020-03-01",
        "min_temp": 5.33,
        "max_temp": 9.815,
        "the_temp": 9.865,
        "wind_speed": 11.590553667777513,
        "wind_direction": 243.50534800847242,
        "air_pressure": 989.5,
        "humidity": 51,
        "visibility": 10.780479499721626,
        "predictability": 75
    },
    {
        "id": 5089920634847232,
        "weather_state_name": "Light Rain",
        "weather_state_abbr": "lr",
        "wind_direction_compass": "WSW",
        "created": "2020-03-01T15:16:01.761744Z",
        "applicable_date": "2020-03-01",
        "min_temp": 5.33,
        "max_temp": 9.815,
        "the_temp": 9.325,
        "wind_speed": 11.590553667777513,
        "wind_direction": 243.50534800847242,
        "air_pressure": 989.5,
        "humidity": 51,
        "visibility": 10.780479499721626,
        "predictability": 75
    },
    {
        "id": 5996345724764160,
        "weather_state_name": "Light Rain",
        "weather_state_abbr": "lr",
        "wind_direction_compass": "SW",
        "created": "2020-03-01T12:16:02.159342Z",
        "applicable_date": "2020-03-01",
        "min_temp": 5.505000000000001,
        "max_temp": 9.575,
        "the_temp": 9.04,
        "wind_speed": 10.184601621628358,
        "wind_direction": 235.33674022881857,
        "air_pressure": 990.5,
        "humidity": 53,
        "visibility": 11.16635101010101,
        "predictability": 75
    },
    {
        "id": 6619113969418240,
        "weather_state_name": "Light Rain",
        "weather_state_abbr": "lr",
        "wind_direction_compass": "WSW",
        "created": "2020-03-01T09:16:01.914639Z",
        "applicable_date": "2020-03-01",
        "min_temp": 5.485,
        "max_temp": 9.01,
        "the_temp": 8.989999999999998,
        "wind_speed": 10.572161888295023,
        "wind_direction": 243.1691596159214,
        "air_pressure": 990.5,
        "humidity": 51,
        "visibility": 12.574999502903047,
        "predictability": 75
    },
    {
        "id": 6618401474609152,
        "weather_state_name": "Light Rain",
        "weather_state_abbr": "lr",
        "wind_direction_compass": "WSW",
        "created": "2020-03-01T06:16:01.820037Z",
        "applicable_date": "2020-03-01",
        "min_temp": 4.755000000000001,
        "max_temp": 9.02,
        "the_temp": 8.969999999999999,
        "wind_speed": 10.527423288295024,
        "wind_direction": 243.1691596159214,
        "air_pressure": 990.5,
        "humidity": 51,
        "visibility": 12.78160542432196,
        "predictability": 75
    },
    {
        "id": 6409494265331712,
        "weather_state_name": "Light Rain",
        "weather_state_abbr": "lr",
        "wind_direction_compass": "WSW",
        "created": "2020-03-01T03:16:02.613205Z",
        "applicable_date": "2020-03-01",
        "min_temp": 4.595000000000001,
        "max_temp": 9.504999999999999,
        "the_temp": 8.91,
        "wind_speed": 10.379699888295024,
        "wind_direction": 243.5016784951761,
        "air_pressure": 990.5,
        "humidity": 52,
        "visibility": 12.862383679312813,
        "predictability": 75
    },
    {
        "id": 6212588134203392,
        "weather_state_name": "Showers",
        "weather_state_abbr": "s",
        "wind_direction_compass": "WSW",
        "created": "2020-03-01T00:16:03.224373Z",
        "applicable_date": "2020-03-01",
        "min_temp": 4.470000000000001,
        "max_temp": 9.335,
        "the_temp": 8.815000000000001,
        "wind_speed": 10.199502452281344,
        "wind_direction": 242.8335245180748,
        "air_pressure": 990.5,
        "humidity": 52,
        "visibility": 12.806460272011453,
        "predictability": 73
    },
    {
        "id": 6622483237044224,
        "weather_state_name": "Showers",
        "weather_state_abbr": "s",
        "wind_direction_compass": "WSW",
        "created": "2020-02-29T21:16:02.020000Z",
        "applicable_date": "2020-03-01",
        "min_temp": 4.470000000000001,
        "max_temp": 9.335,
        "the_temp": 8.745000000000001,
        "wind_speed": 10.348631118948012,
        "wind_direction": 242.8335245180748,
        "air_pressure": 990.0,
        "humidity": 52,
        "visibility": 12.702691282907818,
        "predictability": 73
    },
    {
        "id": 5776975278899200,
        "weather_state_name": "Light Rain",
        "weather_state_abbr": "lr",
        "wind_direction_compass": "WSW",
        "created": "2020-02-29T18:16:03.894713Z",
        "applicable_date": "2020-03-01",
        "min_temp": 4.725,
        "max_temp": 9.09,
        "the_temp": 8.74,
        "wind_speed": 10.237206582534002,
        "wind_direction": 239.8275945034938,
        "air_pressure": 990.0,
        "humidity": 53,
        "visibility": 13.19388521037143,
        "predictability": 75
    },
    {
        "id": 5695168927760384,
        "weather_state_name": "Light Rain",
        "weather_state_abbr": "lr",
        "wind_direction_compass": "WSW",
        "created": "2020-02-29T15:16:01.806381Z",
        "applicable_date": "2020-03-01",
        "min_temp": 4.725,
        "max_temp": 9.09,
        "the_temp": 8.79,
        "wind_speed": 10.416160982534002,
        "wind_direction": 239.8275945034938,
        "air_pressure": 990.0,
        "humidity": 53,
        "visibility": 13.65742811978048,
        "predictability": 75
    },
    {
        "id": 6050466339225600,
        "weather_state_name": "Light Rain",
        "weather_state_abbr": "lr",
        "wind_direction_compass": "WSW",
        "created": "2020-02-29T12:16:02.506409Z",
        "applicable_date": "2020-03-01",
        "min_temp": 4.609999999999999,
        "max_temp": 9.055,
        "the_temp": 8.614999999999998,
        "wind_speed": 9.855684922182455,
        "wind_direction": 239.15971652333656,
        "air_pressure": 989.5,
        "humidity": 53,
        "visibility": 13.642204525570666,
        "predictability": 75
    },
    {
        "id": 6614587342323712,
        "weather_state_name": "Light Rain",
        "weather_state_abbr": "lr",
        "wind_direction_compass": "WSW",
        "created": "2020-02-29T09:16:03.460259Z",
        "applicable_date": "2020-03-01",
        "min_temp": 4.715,
        "max_temp": 9.04,
        "the_temp": 8.675,
        "wind_speed": 9.668832855515788,
        "wind_direction": 239.15971652333656,
        "air_pressure": 989.0,
        "humidity": 57,
        "visibility": 12.478065596914021,
        "predictability": 75
    },
    {
        "id": 4579169860059136,
        "weather_state_name": "Light Rain",
        "weather_state_abbr": "lr",
        "wind_direction_compass": "WSW",
        "created": "2020-02-29T06:16:02.263480Z",
        "applicable_date": "2020-03-01",
        "min_temp": 4.85,
        "max_temp": 9.03,
        "the_temp": 8.504999999999999,
        "wind_speed": 9.994845733550731,
        "wind_direction": 240.83032602017695,
        "air_pressure": 989.0,
        "humidity": 59,
        "visibility": 12.76979937166945,
        "predictability": 75
    },
    {
        "id": 4505953686781952,
        "weather_state_name": "Showers",
        "weather_state_abbr": "s",
        "wind_direction_compass": "WSW",
        "created": "2020-02-29T03:16:02.542451Z",
        "applicable_date": "2020-03-01",
        "min_temp": 4.675000000000001,
        "max_temp": 9.045,
        "the_temp": 8.49,
        "wind_speed": 10.650210966884064,
        "wind_direction": 241.8310195449033,
        "air_pressure": 989.0,
        "humidity": 59,
        "visibility": 13.355441720353138,
        "predictability": 73
    },
    {
        "id": 6353082352926720,
        "weather_state_name": "Showers",
        "weather_state_abbr": "s",
        "wind_direction_compass": "WSW",
        "created": "2020-02-29T00:16:03.861887Z",
        "applicable_date": "2020-03-01",
        "min_temp": 4.535,
        "max_temp": 9.06,
        "the_temp": 8.575,
        "wind_speed": 10.890474075078872,
        "wind_direction": 241.1637569829815,
        "air_pressure": 988.5,
        "humidity": 57,
        "visibility": 13.570125467271136,
        "predictability": 73
    },
    {
        "id": 4739676680224768,
        "weather_state_name": "Showers",
        "weather_state_abbr": "s",
        "wind_direction_compass": "SW",
        "created": "2020-02-28T21:16:03.155174Z",
        "applicable_date": "2020-03-01",
        "min_temp": 4.535,
        "max_temp": 9.06,
        "the_temp": 8.55,
        "wind_speed": 10.450544508412206,
        "wind_direction": 233.67452323432872,
        "air_pressure": 988.0,
        "humidity": 59,
        "visibility": 10.82863576712002,
        "predictability": 73
    },
    {
        "id": 5594546433949696,
        "weather_state_name": "Showers",
        "weather_state_abbr": "s",
        "wind_direction_compass": "SW",
        "created": "2020-02-28T18:16:04.027305Z",
        "applicable_date": "2020-03-01",
        "min_temp": 4.535,
        "max_temp": 8.935,
        "the_temp": 8.475,
        "wind_speed": 9.970683779453326,
        "wind_direction": 234.00826430746326,
        "air_pressure": 988.5,
        "humidity": 62,
        "visibility": 10.593446770858188,
        "predictability": 73
    },
    {
        "id": 4855224026005504,
        "weather_state_name": "Showers",
        "weather_state_abbr": "s",
        "wind_direction_compass": "SW",
        "created": "2020-02-28T15:16:03.302665Z",
        "applicable_date": "2020-03-01",
        "min_temp": 4.535,
        "max_temp": 8.935,
        "the_temp": 8.305,
        "wind_speed": 9.925945179453326,
        "wind_direction": 234.00826430746326,
        "air_pressure": 988.5,
        "humidity": 65,
        "visibility": 8.829063270500278,
        "predictability": 73
    },
    {
        "id": 4506953004875776,
        "weather_state_name": "Heavy Cloud",
        "weather_state_abbr": "hc",
        "wind_direction_compass": "SW",
        "created": "2020-02-28T12:16:04.705876Z",
        "applicable_date": "2020-03-01",
        "min_temp": 4.66,
        "max_temp": 9.22,
        "the_temp": 8.615,
        "wind_speed": 10.114427459829264,
        "wind_direction": 225.31864342437652,
        "air_pressure": 989.0,
        "humidity": 63,
        "visibility": 8.77251849200668,
        "predictability": 71
    },
    {
        "id": 6349911459102720,
        "weather_state_name": "Showers",
        "weather_state_abbr": "s",
        "wind_direction_compass": "SW",
        "created": "2020-02-28T09:16:04.713302Z",
        "applicable_date": "2020-03-01",
        "min_temp": 4.765000000000001,
        "max_temp": 9.765,
        "the_temp": 8.975000000000001,
        "wind_speed": 10.75241782649593,
        "wind_direction": 232.67230796817603,
        "air_pressure": 988.5,
        "humidity": 60,
        "visibility": 9.529037918555634,
        "predictability": 73
    },
    {
        "id": 6601458407440384,
        "weather_state_name": "Showers",
        "weather_state_abbr": "s",
        "wind_direction_compass": "SW",
        "created": "2020-02-28T06:16:04.632600Z",
        "applicable_date": "2020-03-01",
        "min_temp": 4.795,
        "max_temp": 9.690000000000001,
        "the_temp": 8.97,
        "wind_speed": 10.862193194056047,
        "wind_direction": 233.3406016574657,
        "air_pressure": 988.0,
        "humidity": 60,
        "visibility": 9.704575280362683,
        "predictability": 73
    },
    {
        "id": 5367351094542336,
        "weather_state_name": "Heavy Cloud",
        "weather_state_abbr": "hc",
        "wind_direction_compass": "SW",
        "created": "2020-02-28T03:16:01.333610Z",
        "applicable_date": "2020-03-01",
        "min_temp": 4.785,
        "max_temp": 9.71,
        "the_temp": 8.925,
        "wind_speed": 10.885967760722714,
        "wind_direction": 225.6580376151266,
        "air_pressure": 988.0,
        "humidity": 60,
        "visibility": 9.676613576712,
        "predictability": 71
    },
    {
        "id": 5834220574343168,
        "weather_state_name": "Showers",
        "weather_state_abbr": "s",
        "wind_direction_compass": "SW",
        "created": "2020-02-28T00:16:04.350022Z",
        "applicable_date": "2020-03-01",
        "min_temp": 4.779999999999999,
        "max_temp": 9.725,
        "the_temp": 8.780000000000001,
        "wind_speed": 10.651089953421353,
        "wind_direction": 221.56438959062677,
        "air_pressure": 988.0,
        "humidity": 63,
        "visibility": 9.417812475145151,
        "predictability": 73
    },
    {
        "id": 5160245984755712,
        "weather_state_name": "Showers",
        "weather_state_abbr": "s",
        "wind_direction_compass": "SW",
        "created": "2020-02-27T21:16:02.733101Z",
        "applicable_date": "2020-03-01",
        "min_temp": 4.779999999999999,
        "max_temp": 9.725,
        "the_temp": 8.65,
        "wind_speed": 10.643633520088018,
        "wind_direction": 228.9957233079115,
        "air_pressure": 988.0,
        "humidity": 61,
        "visibility": 8.689876123439115,
        "predictability": 73
    },
    {
        "id": 5189640648654848,
        "weather_state_name": "Light Rain",
        "weather_state_abbr": "lr",
        "wind_direction_compass": "SW",
        "created": "2020-02-27T18:16:03.933549Z",
        "applicable_date": "2020-03-01",
        "min_temp": 4.79,
        "max_temp": 9.24,
        "the_temp": 8.8,
        "wind_speed": 11.811890160476153,
        "wind_direction": 232.00356445429645,
        "air_pressure": 988.5,
        "humidity": 58,
        "visibility": 10.39025839099658,
        "predictability": 75
    },
    {
        "id": 6645953152942080,
        "weather_state_name": "Showers",
        "weather_state_abbr": "s",
        "wind_direction_compass": "SW",
        "created": "2020-02-27T15:16:04.690195Z",
        "applicable_date": "2020-03-01",
        "min_temp": 4.79,
        "max_temp": 9.24,
        "the_temp": 8.71,
        "wind_speed": 11.707500093809486,
        "wind_direction": 232.00356445429645,
        "air_pressure": 988.5,
        "humidity": 59,
        "visibility": 10.283693231527877,
        "predictability": 73
    },
    {
        "id": 5963555637559296,
        "weather_state_name": "Light Rain",
        "weather_state_abbr": "lr",
        "wind_direction_compass": "WSW",
        "created": "2020-02-27T12:16:02.260470Z",
        "applicable_date": "2020-03-01",
        "min_temp": 4.800000000000001,
        "max_temp": 9.365,
        "the_temp": 8.805,
        "wind_speed": 11.911310180439566,
        "wind_direction": 237.9906294699133,
        "air_pressure": 988.0,
        "humidity": 59,
        "visibility": 9.815490038177046,
        "predictability": 75
    },
    {
        "id": 6750894303477760,
        "weather_state_name": "Light Rain",
        "weather_state_abbr": "lr",
        "wind_direction_compass": "WSW",
        "created": "2020-02-27T09:16:02.983241Z",
        "applicable_date": "2020-03-01",
        "min_temp": 4.715,
        "max_temp": 9.205,
        "the_temp": 8.855,
        "wind_speed": 12.938974280439567,
        "wind_direction": 247.83306270093436,
        "air_pressure": 988.0,
        "humidity": 57,
        "visibility": 10.998891473793048,
        "predictability": 75
    },
    {
        "id": 5334398318673920,
        "weather_state_name": "Showers",
        "weather_state_abbr": "s",
        "wind_direction_compass": "WSW",
        "created": "2020-02-27T06:16:04.076345Z",
        "applicable_date": "2020-03-01",
        "min_temp": 4.5,
        "max_temp": 8.57,
        "the_temp": 8.084999999999999,
        "wind_speed": 12.863581116607016,
        "wind_direction": 247.16681861038793,
        "air_pressure": 989.5,
        "humidity": 58,
        "visibility": 11.83774258331345,
        "predictability": 73
    },
    {
        "id": 5818269804003328,
        "weather_state_name": "Light Rain",
        "weather_state_abbr": "lr",
        "wind_direction_compass": "WSW",
        "created": "2020-02-27T03:16:04.888209Z",
        "applicable_date": "2020-03-01",
        "min_temp": 4.43,
        "max_temp": 8.715,
        "the_temp": 8.06,
        "wind_speed": 13.679643416607014,
        "wind_direction": 247.16681861038793,
        "air_pressure": 990.0,
        "humidity": 59,
        "visibility": 13.103165016304779,
        "predictability": 75
    },
    {
        "id": 6543086605828096,
        "weather_state_name": "Light Rain",
        "weather_state_abbr": "lr",
        "wind_direction_compass": "WSW",
        "created": "2020-02-27T00:16:02.993484Z",
        "applicable_date": "2020-03-01",
        "min_temp": 4.529999999999999,
        "max_temp": 8.745000000000001,
        "the_temp": 7.97,
        "wind_speed": 13.532586196982955,
        "wind_direction": 246.83354121671803,
        "air_pressure": 991.0,
        "humidity": 59,
        "visibility": 13.008405909488587,
        "predictability": 75
    },
    {
        "id": 5187658252812288,
        "weather_state_name": "Light Rain",
        "weather_state_abbr": "lr",
        "wind_direction_compass": "WSW",
        "created": "2020-02-26T21:16:04.605388Z",
        "applicable_date": "2020-03-01",
        "min_temp": 4.529999999999999,
        "max_temp": 8.745000000000001,
        "the_temp": 8.105,
        "wind_speed": 13.540042630316286,
        "wind_direction": 246.83354121671803,
        "air_pressure": 991.0,
        "humidity": 61,
        "visibility": 10.435929173626024,
        "predictability": 75
    },
    {
        "id": 6210316968919040,
        "weather_state_name": "Light Rain",
        "weather_state_abbr": "lr",
        "wind_direction_compass": "WSW",
        "created": "2020-02-26T18:16:06.322584Z",
        "applicable_date": "2020-03-01",
        "min_temp": 4.140000000000001,
        "max_temp": 9.120000000000001,
        "the_temp": 8.22,
        "wind_speed": 12.92971322073491,
        "wind_direction": 244.50026675861483,
        "air_pressure": 992.0,
        "humidity": 64,
        "visibility": 10.666457885946075,
        "predictability": 75
    },
    {
        "id": 6634615554965504,
        "weather_state_name": "Light Rain",
        "weather_state_abbr": "lr",
        "wind_direction_compass": "WSW",
        "created": "2020-02-26T15:16:03.177864Z",
        "applicable_date": "2020-03-01",
        "min_temp": 4.140000000000001,
        "max_temp": 9.120000000000001,
        "the_temp": 8.235,
        "wind_speed": 13.384555654068242,
        "wind_direction": 237.01966313122415,
        "air_pressure": 992.5,
        "humidity": 65,
        "visibility": 11.367985961982026,
        "predictability": 75
    },
    {
        "id": 5087918735491072,
        "weather_state_name": "Light Rain",
        "weather_state_abbr": "lr",
        "wind_direction_compass": "WSW",
        "created": "2020-02-26T12:16:03.697362Z",
        "applicable_date": "2020-03-01",
        "min_temp": 4.23,
        "max_temp": 9.205,
        "the_temp": 8.535,
        "wind_speed": 13.44047958570747,
        "wind_direction": 238.3528094842302,
        "air_pressure": 991.0,
        "humidity": 64,
        "visibility": 11.807916766086057,
        "predictability": 75
    },
    {
        "id": 6632004214849536,
        "weather_state_name": "Light Rain",
        "weather_state_abbr": "lr",
        "wind_direction_compass": "WSW",
        "created": "2020-02-26T09:16:02.851580Z",
        "applicable_date": "2020-03-01",
        "min_temp": 4.21,
        "max_temp": 8.530000000000001,
        "the_temp": 8.465,
        "wind_speed": 13.1887035190408,
        "wind_direction": 238.3528094842302,
        "air_pressure": 990.5,
        "humidity": 59,
        "visibility": 9.391093513878946,
        "predictability": 75
    },
    {
        "id": 4654823494385664,
        "weather_state_name": "Light Rain",
        "weather_state_abbr": "lr",
        "wind_direction_compass": "SW",
        "created": "2020-02-26T06:16:02.220838Z",
        "applicable_date": "2020-03-01",
        "min_temp": 4.345000000000001,
        "max_temp": 8.575,
        "the_temp": 8.805,
        "wind_speed": 12.922343366083405,
        "wind_direction": 234.67708478665435,
        "air_pressure": 988.0,
        "humidity": 60,
        "visibility": 9.403520937723695,
        "predictability": 75
    },
    {
        "id": 6055820125011968,
        "weather_state_name": "Light Rain",
        "weather_state_abbr": "lr",
        "wind_direction_compass": "SW",
        "created": "2020-02-26T03:16:01.922640Z",
        "applicable_date": "2020-03-01",
        "min_temp": 4.365,
        "max_temp": 8.605,
        "the_temp": 8.85,
        "wind_speed": 12.342703032750073,
        "wind_direction": 235.34412982709168,
        "air_pressure": 988.0,
        "humidity": 62,
        "visibility": 9.67940974707707,
        "predictability": 75
    },
    {
        "id": 6480947555860480,
        "weather_state_name": "Heavy Rain",
        "weather_state_abbr": "hr",
        "wind_direction_compass": "WSW",
        "created": "2020-02-26T00:16:03.816899Z",
        "applicable_date": "2020-03-01",
        "min_temp": 4.470000000000001,
        "max_temp": 8.600000000000001,
        "the_temp": 8.12,
        "wind_speed": 10.208829436093215,
        "wind_direction": 241.49999999999997,
        "air_pressure": 993.0,
        "humidity": 62,
        "visibility": 9.999726596675416,
        "predictability": 77
    },
    {
        "id": 5107318096134144,
        "weather_state_name": "Heavy Rain",
        "weather_state_abbr": "hr",
        "wind_direction_compass": "WSW",
        "created": "2020-02-25T21:16:04.795062Z",
        "applicable_date": "2020-03-01",
        "min_temp": 4.470000000000001,
        "max_temp": 8.600000000000001,
        "the_temp": 8.12,
        "wind_speed": 10.208829436093215,
        "wind_direction": 241.49999999999997,
        "air_pressure": 993.0,
        "humidity": 62,
        "visibility": 9.999726596675416,
        "predictability": 77
    },
    {
        "id": 6713755050180608,
        "weather_state_name": "Heavy Rain",
        "weather_state_abbr": "hr",
        "wind_direction_compass": "SW",
        "created": "2020-02-25T18:16:04.605475Z",
        "applicable_date": "2020-03-01",
        "min_temp": 4.245,
        "max_temp": 8.865,
        "the_temp": 6.96,
        "wind_speed": 6.9749258331344945,
        "wind_direction": 231.0,
        "air_pressure": 995.0,
        "humidity": 75,
        "visibility": 9.999726596675416,
        "predictability": 77
    },
    {
        "id": 6435941910577152,
        "weather_state_name": "Heavy Rain",
        "weather_state_abbr": "hr",
        "wind_direction_compass": "SW",
        "created": "2020-02-25T15:16:05.705823Z",
        "applicable_date": "2020-03-01",
        "min_temp": 4.245,
        "max_temp": 8.865,
        "the_temp": 6.96,
        "wind_speed": 6.9749258331344945,
        "wind_direction": 231.0,
        "air_pressure": 995.0,
        "humidity": 75,
        "visibility": 9.999726596675416,
        "predictability": 77
    },
    {
        "id": 4773344056442880,
        "weather_state_name": "Heavy Rain",
        "weather_state_abbr": "hr",
        "wind_direction_compass": "WSW",
        "created": "2020-02-25T12:16:05.071560Z",
        "applicable_date": "2020-03-01",
        "min_temp": 4.075,
        "max_temp": 9.025,
        "the_temp": 8.31,
        "wind_speed": 7.897662053606936,
        "wind_direction": 242.5,
        "air_pressure": 991.0,
        "humidity": 62,
        "visibility": 9.999726596675416,
        "predictability": 77
    },
    {
        "id": 5655283823017984,
        "weather_state_name": "Heavy Rain",
        "weather_state_abbr": "hr",
        "wind_direction_compass": "WSW",
        "created": "2020-02-25T09:16:05.536668Z",
        "applicable_date": "2020-03-01",
        "min_temp": 3.7800000000000002,
        "max_temp": 9.085,
        "the_temp": 8.31,
        "wind_speed": 8.012662053606936,
        "wind_direction": 241.5,
        "air_pressure": 991.0,
        "humidity": 62,
        "visibility": 9.310625944484212,
        "predictability": 77
    },
    {
        "id": 4657355444715520,
        "weather_state_name": "Showers",
        "weather_state_abbr": "s",
        "wind_direction_compass": "WSW",
        "created": "2020-02-25T06:16:04.783133Z",
        "applicable_date": "2020-03-01",
        "min_temp": 2.86,
        "max_temp": 8.895,
        "the_temp": 6.98,
        "wind_speed": 7.568381651157242,
        "wind_direction": 244.5,
        "air_pressure": 1000.0,
        "humidity": 64,
        "visibility": 9.310625944484212,
        "predictability": 73
    },
    {
        "id": 4792658700533760,
        "weather_state_name": "Light Cloud",
        "weather_state_abbr": "lc",
        "wind_direction_compass": "WSW",
        "created": "2020-02-25T03:16:05.882792Z",
        "applicable_date": "2020-03-01",
        "min_temp": 3.1449999999999996,
        "max_temp": 9.03,
        "the_temp": 6.98,
        "wind_speed": 7.668381651157242,
        "wind_direction": 246.49999999999997,
        "air_pressure": 1000.0,
        "humidity": 61,
        "visibility": 9.999726596675416,
        "predictability": 70
    },
    {
        "id": 5796645180538880,
        "weather_state_name": "Light Cloud",
        "weather_state_abbr": "lc",
        "wind_direction_compass": "W",
        "created": "2020-02-25T00:16:05.394371Z",
        "applicable_date": "2020-03-01",
        "min_temp": 3.535,
        "max_temp": 9.205,
        "the_temp": 7.48,
        "wind_speed": 7.811297025371829,
        "wind_direction": 259.0,
        "air_pressure": 1001.0,
        "humidity": 55,
        "visibility": 9.999726596675416,
        "predictability": 70
    },
    {
        "id": 6327375765700608,
        "weather_state_name": "Light Cloud",
        "weather_state_abbr": "lc",
        "wind_direction_compass": "W",
        "created": "2020-02-24T21:16:07.531404Z",
        "applicable_date": "2020-03-01",
        "min_temp": 3.535,
        "max_temp": 9.205,
        "the_temp": 7.48,
        "wind_speed": 7.811297025371829,
        "wind_direction": 259.0,
        "air_pressure": 1001.0,
        "humidity": 55,
        "visibility": 9.999726596675416,
        "predictability": 70
    },
    {
        "id": 5425783545790464,
        "weather_state_name": "Heavy Cloud",
        "weather_state_abbr": "hc",
        "wind_direction_compass": "WNW",
        "created": "2020-02-24T18:16:08.301907Z",
        "applicable_date": "2020-03-01",
        "min_temp": 3.16,
        "max_temp": 8.345,
        "the_temp": 6.79,
        "wind_speed": 9.272279090113736,
        "wind_direction": 296.0,
        "air_pressure": 1006.0,
        "humidity": 58,
        "visibility": 9.999726596675416,
        "predictability": 71
    },
    {
        "id": 6440335687286784,
        "weather_state_name": "Heavy Cloud",
        "weather_state_abbr": "hc",
        "wind_direction_compass": "WNW",
        "created": "2020-02-24T15:16:07.022815Z",
        "applicable_date": "2020-03-01",
        "min_temp": 3.16,
        "max_temp": 8.345,
        "the_temp": 6.79,
        "wind_speed": 9.272279090113736,
        "wind_direction": 296.0,
        "air_pressure": 1006.0,
        "humidity": 58,
        "visibility": 9.999726596675416,
        "predictability": 71
    },
    {
        "id": 4800340341817344,
        "weather_state_name": "Light Rain",
        "weather_state_abbr": "lr",
        "wind_direction_compass": "W",
        "created": "2020-02-24T12:16:07.872220Z",
        "applicable_date": "2020-03-01",
        "min_temp": 2.91,
        "max_temp": 8.605,
        "the_temp": 6.59,
        "wind_speed": 8.949166070150323,
        "wind_direction": 274.5,
        "air_pressure": 1006.0,
        "humidity": 53,
        "visibility": 9.999726596675416,
        "predictability": 75
    },
    {
        "id": 6691472759848960,
        "weather_state_name": "Showers",
        "weather_state_abbr": "s",
        "wind_direction_compass": "WNW",
        "created": "2020-02-24T09:16:08.358214Z",
        "applicable_date": "2020-03-01",
        "min_temp": 2.395,
        "max_temp": 7.91,
        "the_temp": 6.59,
        "wind_speed": 6.684166070150322,
        "wind_direction": 293.5,
        "air_pressure": 1006.0,
        "humidity": 56,
        "visibility": 9.999726596675416,
        "predictability": 73
    },
    {
        "id": 4874525768417280,
        "weather_state_name": "Heavy Rain",
        "weather_state_abbr": "hr",
        "wind_direction_compass": "NNW",
        "created": "2020-02-24T06:16:07.461002Z",
        "applicable_date": "2020-03-01",
        "min_temp": 1.78,
        "max_temp": 7.17,
        "the_temp": 5.56,
        "wind_speed": 5.273653463771574,
        "wind_direction": 333.0,
        "air_pressure": 996.0,
        "humidity": 63,
        "visibility": 9.999726596675416,
        "predictability": 77
    },
    {
        "id": 4964273405034496,
        "weather_state_name": "Heavy Rain",
        "weather_state_abbr": "hr",
        "wind_direction_compass": "N",
        "created": "2020-02-24T03:16:07.564242Z",
        "applicable_date": "2020-03-01",
        "min_temp": 1.615,
        "max_temp": 7.18,
        "the_temp": 5.56,
        "wind_speed": 5.718653463771574,
        "wind_direction": 354.5,
        "air_pressure": 996.0,
        "humidity": 60,
        "visibility": 9.999726596675416,
        "predictability": 77
    },
    {
        "id": 6187124413956096,
        "weather_state_name": "Heavy Cloud",
        "weather_state_abbr": "hc",
        "wind_direction_compass": "NNE",
        "created": "2020-02-24T00:16:08.142474Z",
        "applicable_date": "2020-03-01",
        "min_temp": 1.24,
        "max_temp": 7.22,
        "the_temp": 5.73,
        "wind_speed": 6.162933866221268,
        "wind_direction": 19.500000000000004,
        "air_pressure": 1016.0,
        "humidity": 58,
        "visibility": 9.999726596675416,
        "predictability": 71
    },
    {
        "id": 4584450790785024,
        "weather_state_name": "Heavy Cloud",
        "weather_state_abbr": "hc",
        "wind_direction_compass": "NNE",
        "created": "2020-02-23T21:16:11.248985Z",
        "applicable_date": "2020-03-01",
        "min_temp": 1.24,
        "max_temp": 7.22,
        "the_temp": 5.73,
        "wind_speed": 6.162933866221268,
        "wind_direction": 19.500000000000004,
        "air_pressure": 1016.0,
        "humidity": 58,
        "visibility": 9.999726596675416,
        "predictability": 71
    },
    {
        "id": 6130305486290944,
        "weather_state_name": "Heavy Cloud",
        "weather_state_abbr": "hc",
        "wind_direction_compass": "WNW",
        "created": "2020-02-23T18:16:11.965067Z",
        "applicable_date": "2020-03-01",
        "min_temp": 0.915,
        "max_temp": 7.87,
        "the_temp": 5.26,
        "wind_speed": 6.127736220472441,
        "wind_direction": 288.5,
        "air_pressure": 1018.0,
        "humidity": 52,
        "visibility": 9.999726596675416,
        "predictability": 71
    },
    {
        "id": 5322867002572800,
        "weather_state_name": "Heavy Cloud",
        "weather_state_abbr": "hc",
        "wind_direction_compass": "WNW",
        "created": "2020-02-23T15:16:10.150224Z",
        "applicable_date": "2020-03-01",
        "min_temp": 0.915,
        "max_temp": 7.87,
        "the_temp": 5.26,
        "wind_speed": 6.127736220472441,
        "wind_direction": 288.5,
        "air_pressure": 1018.0,
        "humidity": 52,
        "visibility": 9.999726596675416,
        "predictability": 71
    },
    {
        "id": 4636275342573568,
        "weather_state_name": "Hail",
        "weather_state_abbr": "h",
        "wind_direction_compass": "WNW",
        "created": "2020-02-23T12:16:11.196042Z",
        "applicable_date": "2020-03-01",
        "min_temp": 0.41500000000000004,
        "max_temp": 6.050000000000001,
        "the_temp": 1.16,
        "wind_speed": 7.407760876481349,
        "wind_direction": 296.5,
        "air_pressure": 1004.0,
        "humidity": 74,
        "visibility": 9.999726596675416,
        "predictability": 82
    },
    {
        "id": 6597001732947968,
        "weather_state_name": "Hail",
        "weather_state_abbr": "h",
        "wind_direction_compass": "WNW",
        "created": "2020-02-23T09:16:10.404991Z",
        "applicable_date": "2020-03-01",
        "min_temp": 1.435,
        "max_temp": 5.99,
        "the_temp": 1.16,
        "wind_speed": 7.177760876481349,
        "wind_direction": 283.0,
        "air_pressure": 1004.0,
        "humidity": 87,
        "visibility": 9.755527718126142,
        "predictability": 82
    },
    {
        "id": 6443985847451648,
        "weather_state_name": "Heavy Rain",
        "weather_state_abbr": "hr",
        "wind_direction_compass": "WNW",
        "created": "2020-02-23T06:16:10.548597Z",
        "applicable_date": "2020-03-01",
        "min_temp": 3.135,
        "max_temp": 7.81,
        "the_temp": 6.55,
        "wind_speed": 6.171139545056867,
        "wind_direction": 286.0,
        "air_pressure": 1003.0,
        "humidity": 76,
        "visibility": 9.755527718126142,
        "predictability": 77
    },
    {
        "id": 5132887043080192,
        "weather_state_name": "Heavy Rain",
        "weather_state_abbr": "hr",
        "wind_direction_compass": "WNW",
        "created": "2020-02-23T03:16:11.676706Z",
        "applicable_date": "2020-03-01",
        "min_temp": 3.15,
        "max_temp": 7.18,
        "the_temp": 6.55,
        "wind_speed": 2.392279090113736,
        "wind_direction": 301.0,
        "air_pressure": 1003.0,
        "humidity": 56,
        "visibility": null,
        "predictability": 77
    },
    {
        "id": 5918786400026624,
        "weather_state_name": "Heavy Cloud",
        "weather_state_abbr": "hc",
        "wind_direction_compass": "NE",
        "created": "2020-02-23T00:16:11.642548Z",
        "applicable_date": "2020-03-01",
        "min_temp": 1.51,
        "max_temp": 6.66,
        "the_temp": 5.92,
        "wind_speed": 1.5099319971367215,
        "wind_direction": 41.0,
        "air_pressure": 1012.0,
        "humidity": 49,
        "visibility": null,
        "predictability": 71
    },
    {
        "id": 6566678726967296,
        "weather_state_name": "Heavy Cloud",
        "weather_state_abbr": "hc",
        "wind_direction_compass": "NE",
        "created": "2020-02-22T21:16:15.158846Z",
        "applicable_date": "2020-03-01",
        "min_temp": 1.51,
        "max_temp": 6.66,
        "the_temp": 5.92,
        "wind_speed": 1.5099319971367215,
        "wind_direction": 41.0,
        "air_pressure": 1012.0,
        "humidity": 49,
        "visibility": null,
        "predictability": 71
    },
    {
        "id": 4902999925194752,
        "weather_state_name": "Heavy Cloud",
        "weather_state_abbr": "hc",
        "wind_direction_compass": "W",
        "created": "2020-02-22T18:16:13.596051Z",
        "applicable_date": "2020-03-01",
        "min_temp": 3.06,
        "max_temp": 6.99,
        "the_temp": 4.75,
        "wind_speed": 3.641235186510777,
        "wind_direction": 276.0,
        "air_pressure": 997.0,
        "humidity": 73,
        "visibility": null,
        "predictability": 71
    },
    {
        "id": 4722288077307904,
        "weather_state_name": "Heavy Cloud",
        "weather_state_abbr": "hc",
        "wind_direction_compass": "W",
        "created": "2020-02-22T15:16:13.185844Z",
        "applicable_date": "2020-03-01",
        "min_temp": 3.06,
        "max_temp": 6.99,
        "the_temp": 4.75,
        "wind_speed": 3.641235186510777,
        "wind_direction": 276.0,
        "air_pressure": 997.0,
        "humidity": 73,
        "visibility": null,
        "predictability": 71
    },
    {
        "id": 4522052943872000,
        "weather_state_name": "Heavy Rain",
        "weather_state_abbr": "hr",
        "wind_direction_compass": "W",
        "created": "2020-02-22T12:16:14.830289Z",
        "applicable_date": "2020-03-01",
        "min_temp": 3.8,
        "max_temp": 7.77,
        "the_temp": 5.85,
        "wind_speed": 3.094428537341923,
        "wind_direction": 267.0,
        "air_pressure": 990.0,
        "humidity": 64,
        "visibility": null,
        "predictability": 77
    },
    {
        "id": 4741167973400576,
        "weather_state_name": "Heavy Rain",
        "weather_state_abbr": "hr",
        "wind_direction_compass": "W",
        "created": "2020-02-22T09:16:14.519320Z",
        "applicable_date": "2020-03-01",
        "min_temp": 3.8,
        "max_temp": 7.77,
        "the_temp": 5.85,
        "wind_speed": 3.094428537341923,
        "wind_direction": 267.0,
        "air_pressure": 990.0,
        "humidity": 64,
        "visibility": null,
        "predictability": 77
    },
    {
        "id": 4515237728354304,
        "weather_state_name": "Heavy Rain",
        "weather_state_abbr": "hr",
        "wind_direction_compass": "W",
        "created": "2020-02-22T06:16:13.739156Z",
        "applicable_date": "2020-03-01",
        "min_temp": 2.66,
        "max_temp": 7.75,
        "the_temp": 7.05,
        "wind_speed": 3.16277936848803,
        "wind_direction": 276.0,
        "air_pressure": 1001.0,
        "humidity": 45,
        "visibility": null,
        "predictability": 77
    },
    {
        "id": 6110297490194432,
        "weather_state_name": "Heavy Rain",
        "weather_state_abbr": "hr",
        "wind_direction_compass": "W",
        "created": "2020-02-22T03:16:13.526702Z",
        "applicable_date": "2020-03-01",
        "min_temp": 2.66,
        "max_temp": 7.75,
        "the_temp": 7.05,
        "wind_speed": 3.16277936848803,
        "wind_direction": 276.0,
        "air_pressure": 1001.0,
        "humidity": 45,
        "visibility": null,
        "predictability": 77
    },
    {
        "id": 6098469376753664,
        "weather_state_name": "Heavy Cloud",
        "weather_state_abbr": "hc",
        "wind_direction_compass": "NW",
        "created": "2020-02-22T00:16:13.254599Z",
        "applicable_date": "2020-03-01",
        "min_temp": 2.74,
        "max_temp": 5.66,
        "the_temp": 5.66,
        "wind_speed": 3.75929571303587,
        "wind_direction": 325.0,
        "air_pressure": 1006.0,
        "humidity": 46,
        "visibility": null,
        "predictability": 71
    }
]